LICENSE
MANIFEST.in
ReadMe.md
TODO.md
requirements.txt
setup.py
docs/test.txt
pic/TAIScoreLogo.png
score/__init__.py
score/base.py
score/deploy.py
score/eda.py
score/features.py
score/interpreter.py
score/metrics.py
score/model_selection.py
score/monitor.py
score/pipeline.py
score/plot.py
score/preprocessing.py
score/report.py
score/risk_rules.py
score/version.py
score.egg-info/PKG-INFO
score.egg-info/SOURCES.txt
score.egg-info/dependency_links.txt
score.egg-info/entry_points.txt
score.egg-info/requires.txt
score.egg-info/top_level.txt
score/ml/__init__.py
score/score_card/__init__.py
score/score_card/merge.py
score/score_card/__pycache__/__init__.cpython-36.pyc
tests/test_merge.ipynb