Metadata-Version: 2.1
Name: score
Version: 0.0.1a0
Summary: TAIScore
Home-page: UNKNOWN
Author: Spencer
Author-email: spencercs.ai@gmail.com
License: not open source
Platform: UNKNOWN
Classifier: Operating System :: POSIX
Classifier: Operating System :: Microsoft :: Windows
Classifier: Operating System :: MacOS :: MacOS X
Classifier: Programming Language :: Python :: 3.5
Classifier: Programming Language :: Python :: 3.6
Requires-Python: >3.5
